{"note":"Don't delete this file! It's used internally to help with page regeneration.","name":"Arjo129.github.com","tagline":"Where things that work don't","body":"###Random stuff\r\nThis site houses a collection of programs created by me, Arjo Chakravarty. The pages serve as a start place for people to see the documentation and download the source code. My current projects include a speech recognition library for the arduino.\r\n* [µSpeech Speech recognition framework](http://arjo129.github.com/uSpeech/)","google":""}